github_issues_import/__about__.py
github_issues_import/__init__.py
github_issues_import/client.py
github_issues_import/models.py
github_issues_import-0.4.3.dist-info/METADATA
github_issues_import-0.4.3.dist-info/WHEEL
github_issues_import-0.4.3.dist-info/licenses/LICENSE
github_issues_import-0.4.3.dist-info/RECORD
