Metadata-Version: 2.4
Name: github-issues-import
Version: 0.4.3
Summary: Modern, typesafe Python client for GitHub's unofficial API for importing issues
Author-email: "Yury V. Zaytsev" <yury@shurup.com>
License-Expression: MIT
License-File: LICENSE
Keywords: github,github-api,httpx,import,pydantic
Classifier: Development Status :: 5 - Production/Stable
Classifier: Intended Audience :: Developers
Classifier: License :: OSI Approved :: MIT License
Classifier: Programming Language :: Python :: 3
Classifier: Programming Language :: Python :: 3 :: Only
Classifier: Programming Language :: Python :: 3.11
Classifier: Programming Language :: Python :: 3.12
Classifier: Programming Language :: Python :: 3.13
Classifier: Topic :: Software Development :: Libraries :: Python Modules
Requires-Python: >=3.11
Requires-Dist: httpx
Requires-Dist: pydantic>=2.0
